LICENSE
README.md
setup.py
testneo/__init__.py
testneo.egg-info/PKG-INFO
testneo.egg-info/SOURCES.txt
testneo.egg-info/dependency_links.txt
testneo.egg-info/top_level.txt
testneo.egg-info/zip-safe
testneo/log/__init__.py
testneo/log/myprint.py
testneo/log/settings.py
testneo/log/tests/__init__.py
testneo/log/tests/test_print.py